Metadata-Version: 2.1
Name: django-template-url-optional
Version: 2020.7.1
Summary: django url tag with optional arguments
Home-page: https://github.com/andrewp-as-is/django-template-url-optional.py
License: Unlicense
Keywords: django template url
Platform: UNKNOWN
Classifier: Framework :: Django
Classifier: License :: Public Domain
Classifier: Operating System :: OS Independent
Classifier: Programming Language :: Python :: 3
